grai_source_looker/__init__.py
grai_source_looker/adapters.py
grai_source_looker/api/__init__.py
grai_source_looker/api/api_models.py
grai_source_looker/base.py
grai_source_looker/loader.py
grai_source_looker/mock_tools.py
grai_source_looker/models.py
grai_source_looker/package_definitions.py
grai_source_looker/py.typed
grai_source_looker-0.0.3.dist-info/METADATA
grai_source_looker-0.0.3.dist-info/WHEEL
grai_source_looker-0.0.3.dist-info/RECORD
